pathlike_typing/__init__.py
pathlike_typing-1.0.0.dist-info/licenses/LICENSE
pathlike_typing-1.0.0.dist-info/METADATA
pathlike_typing-1.0.0.dist-info/WHEEL
pathlike_typing-1.0.0.dist-info/top_level.txt
pathlike_typing-1.0.0.dist-info/RECORD
