Metadata-Version: 2.4
Name: pathlike-typing
Version: 1.0.0
Summary: Lightweight Python library providing PathLike type alias for path annotations
Home-page: https://github.com/MagIlyasDOMA/pathlike-typing
Author: Маг Ильяс DOMA (MagIlyasDOMA)
Author-email: magilyas.doma.09@list.ru
License: MIT
Project-URL: Source, https://github.com/MagIlyasDOMA/pathlike-typing
Keywords: typing,path,pathlib,type-hints,annotations
Classifier: Development Status :: 5 - Production/Stable
Classifier: Intended Audience :: Developers
Classifier: License :: OSI Approved :: MIT License
Classifier: Operating System :: OS Independent
Classifier: Programming Language :: Python :: 3
Classifier: Programming Language :: Python :: 3.6
Classifier: Programming Language :: Python :: 3.7
Classifier: Programming Language :: Python :: 3.8
Classifier: Programming Language :: Python :: 3.9
Classifier: Programming Language :: Python :: 3.10
Classifier: Programming Language :: Python :: 3.11
Classifier: Programming Language :: Python :: 3.12
Classifier: Programming Language :: Python :: 3.13
Classifier: Programming Language :: Python :: 3.14
Classifier: Topic :: Software Development :: Libraries :: Python Modules
Classifier: Typing :: Typed
Requires-Python: >=3.6
License-File: LICENSE
Dynamic: author
Dynamic: author-email
Dynamic: classifier
Dynamic: description
Dynamic: description-content-type
Dynamic: home-page
Dynamic: keywords
Dynamic: license
Dynamic: license-file
Dynamic: project-url
Dynamic: requires-python
Dynamic: summary
